{
    "conversion": {
        "rename_keys": {},
        "change_values": [
            [
                "calculateCoulombicEfficiency",
                ["Discharge_Capacity(Ah)", "Charge_Capacity(Ah)"],
                [0],
                "coulombic_efficiency"
            ],
            ["calculateMilliampereHoursPerGramMass", ["Discharge_Capacity(Ah)"], [5], "mAh/g"]
        ],
        "add_values": [
            ["recordDate", "recorded_at"],
            ["recordFileName", "file_name"],
            ["recordNull", "switch_off"],
            ["recordNull", "test_condition"],
            ["recordOne", "volt/cell(V)"]
        ],
        "map_object": {
            "Charge_Capacity(Ah)": "charge_capacity(Ah)",
            "Charge_Energy(Wh)": "charge_energy(Wh)",
            "coulombic_efficiency": "coulombic_efficiency",
            "Current(A)": "current(A)",
            "Cycle_Index": "cycle_index",
            "date_time": "date_time",
            "Discharge_Capacity(Ah)": "discharge_capacity(Ah)",
            "Discharge_Energy(Wh)": "discharge_energy(Wh)",
            "file_name": "file_name",
            "mAh/g": "mAh/g",
            "Power(W)": "power(W)",
            "recorded_at": "recorded_at",
            "Step_Index": "step_index",
            "Step_Time(s)": "step_time(s)",
            "switch_off": "switch_off",
            "test_condition": "test_condition",
            "Test_Time(s)": "test_time(s)",
            "volt/cell(V)": "volt/cell(V)",
            "Voltage(V)": "voltage(V)"
        },
        "date": ["date_time", "recorded_at"]
    },
    "file": {
        "file_extension": "xlsx",
        "profile_name": "arbin",
        "worksheet_number": 1
    }
}
